{
  "PagePath": "/research/",
  "Url": "https://anthro.wsu.edu/research/",
  "FinalUrl": null,
  "Title": "Research | Department of Anthropology | Washington State University",
  "StatusCode": 0,
  "Success": false,
  "HtmlSizeBytes": 216005,
  "ScreenshotSizeBytes": 374835,
  "CredentialUsed": null,
  "ConsoleErrorCount": 0,
  "ConsoleWarningCount": 0,
  "Screenshots": [
    {
      "FileName": "01-page-loaded.png",
      "Label": "page-loaded",
      "StepNumber": 1,
      "FileSize": 374835
    }
  ],
  "ImageCount": 1,
  "ImagesTotalSizeBytes": 137064,
  "ImagesMissingAlt": 0,
  "Images": [
    {
      "FileName": "college-hall_360x265.jpg",
      "SourceUrl": "https://wpcdn.web.wsu.edu/wp-cas/uploads/sites/1028/2015/10/college-hall_360x265.jpg",
      "AltText": "College Hall, Washington State University",
      "FileSize": 137064
    }
  ],
  "ErrorMessage": null,
  "Headers": null,
  "CapturedAt": "2026-02-16T20:39:31.3964046Z"
}