{
  "PagePath": "/apply/additional-application-types/",
  "Url": "https://admission.wsu.edu/apply/additional-application-types/",
  "FinalUrl": null,
  "Title": "Additional Application Types | Admissions | Washington State University",
  "StatusCode": 200,
  "Success": true,
  "HtmlSizeBytes": 90728,
  "ScreenshotSizeBytes": 431809,
  "CredentialUsed": null,
  "ConsoleErrorCount": 0,
  "ConsoleWarningCount": 0,
  "Screenshots": [
    {
      "FileName": "01-page-loaded.jpg",
      "Label": "page-loaded",
      "StepNumber": 1,
      "FileSize": 431809
    }
  ],
  "ImageCount": 0,
  "ImagesMissingAlt": 0,
  "Images": [],
  "Accessibility": {
    "ToolsRun": [
      "axe",
      "htmlcheck"
    ],
    "ToolsSkipped": [
      "wave"
    ],
    "TotalViolations": 9,
    "Critical": 1,
    "Serious": 8,
    "Moderate": 0,
    "Minor": 0,
    "ByTool": {
      "axe": {
        "Total": 3,
        "Critical": 1,
        "Serious": 2,
        "Moderate": 0,
        "Minor": 0
      },
      "htmlcheck": {
        "Total": 6,
        "Critical": 0,
        "Serious": 6,
        "Moderate": 0,
        "Minor": 0
      }
    }
  },
  "ErrorMessage": null,
  "Headers": {
    "content-encoding": "gzip",
    "content-type": "text/html; charset=UTF-8",
    "date": "Thu, 19 Feb 2026 02:08:16 GMT",
    "etag": "\u00224a95ed3a3c56c39a51e53dd8e4c461aa\u0022",
    "last-modified": "Thu, 19 Feb 2026 02:01:37 GMT",
    "link": "\u003Chttps://admission.wsu.edu/wp-json/\u003E; rel=\u0022https://api.w.org/\u0022, \u003Chttps://admission.wsu.edu/wp-json/wp/v2/pages/73\u003E; rel=\u0022alternate\u0022; type=\u0022application/json\u0022, \u003Chttps://admission.wsu.edu/?p=73\u003E; rel=shortlink",
    "server": "nginx",
    "vary": "Accept-Encoding",
    "x-cache": "EXPIRED",
    "x-cache-status": "EXPIRED"
  },
  "CapturedAt": "2026-02-19T02:08:16.5328849Z"
}