{
  "PagePath": "/visit/campus-tours/",
  "Url": "https://admission.wsu.edu/visit/campus-tours/",
  "FinalUrl": null,
  "Title": "Campus Tours | Admissions | Washington State University",
  "StatusCode": 200,
  "Success": true,
  "HtmlSizeBytes": 93334,
  "ScreenshotSizeBytes": 328444,
  "CredentialUsed": null,
  "ConsoleErrorCount": 0,
  "ConsoleWarningCount": 0,
  "Screenshots": [
    {
      "FileName": "01-page-loaded.jpg",
      "Label": "page-loaded",
      "StepNumber": 1,
      "FileSize": 328444
    }
  ],
  "ImageCount": 4,
  "ImagesMissingAlt": 4,
  "Images": [
    {
      "SourceUrl": "https://s3.wp.wsu.edu/uploads/sites/3144/2022/12/Stephenson-Complex_0043-1900x1267-1-792x528.jpg",
      "AltText": ""
    },
    {
      "SourceUrl": "https://s3.wp.wsu.edu/uploads/sites/3144/2022/11/Washington-State-Football-Stadium-2-980x434-1.jpg",
      "AltText": ""
    },
    {
      "SourceUrl": "https://s3.wp.wsu.edu/uploads/sites/3144/2022/12/Students-Return-for-Fall-2022-792x523.jpg",
      "AltText": ""
    },
    {
      "SourceUrl": "https://s3.wp.wsu.edu/uploads/sites/3144/2022/11/library-road-e1605824401570-792x564-1.jpg",
      "AltText": ""
    }
  ],
  "Accessibility": {
    "ToolsRun": [
      "axe",
      "htmlcheck"
    ],
    "ToolsSkipped": [
      "wave"
    ],
    "TotalViolations": 9,
    "Critical": 1,
    "Serious": 8,
    "Moderate": 0,
    "Minor": 0,
    "ByTool": {
      "axe": {
        "Total": 3,
        "Critical": 1,
        "Serious": 2,
        "Moderate": 0,
        "Minor": 0
      },
      "htmlcheck": {
        "Total": 6,
        "Critical": 0,
        "Serious": 6,
        "Moderate": 0,
        "Minor": 0
      }
    }
  },
  "ErrorMessage": null,
  "Headers": {
    "content-encoding": "gzip",
    "content-type": "text/html; charset=UTF-8",
    "date": "Thu, 19 Feb 2026 02:14:05 GMT",
    "etag": "\u0022728346dcc3d1463577ca8aa3c54f6421\u0022",
    "last-modified": "Thu, 19 Feb 2026 01:37:36 GMT",
    "link": "\u003Chttps://admission.wsu.edu/wp-json/\u003E; rel=\u0022https://api.w.org/\u0022, \u003Chttps://admission.wsu.edu/wp-json/wp/v2/pages/34\u003E; rel=\u0022alternate\u0022; type=\u0022application/json\u0022, \u003Chttps://admission.wsu.edu/?p=34\u003E; rel=shortlink",
    "server": "nginx",
    "vary": "Accept-Encoding",
    "x-cache": "EXPIRED",
    "x-cache-status": "EXPIRED"
  },
  "CapturedAt": "2026-02-19T02:14:05.4200368Z"
}