{
  "PagePath": "/",
  "Url": "https://fall-alive.wsu.edu/",
  "FinalUrl": null,
  "Title": null,
  "StatusCode": 0,
  "Success": false,
  "HtmlSizeBytes": 0,
  "ScreenshotSizeBytes": 0,
  "CredentialUsed": null,
  "ConsoleErrorCount": 0,
  "ConsoleWarningCount": 0,
  "Screenshots": [],
  "ImageCount": 0,
  "ImagesMissingAlt": 0,
  "Images": [],
  "Accessibility": null,
  "ErrorMessage": "net::ERR_ABORTED at https://fall-alive.wsu.edu/\nCall log:\n  - navigating to \u0022https://fall-alive.wsu.edu/\u0022, waiting until \u0022networkidle\u0022",
  "Headers": null,
  "CapturedAt": "2026-02-18T18:45:10.81613Z"
}