{
  "PagePath": "/contact/",
  "Url": "https://gsc.wsu.edu/contact/",
  "FinalUrl": null,
  "Title": null,
  "StatusCode": 0,
  "Success": false,
  "HtmlSizeBytes": 0,
  "ScreenshotSizeBytes": 0,
  "CredentialUsed": null,
  "ConsoleErrorCount": 0,
  "ConsoleWarningCount": 0,
  "Screenshots": [],
  "ErrorMessage": "net::ERR_NAME_NOT_RESOLVED at https://gsc.wsu.edu/contact/\nCall log:\n  - navigating to \u0022https://gsc.wsu.edu/contact/\u0022, waiting until \u0022networkidle\u0022",
  "Headers": null,
  "CapturedAt": "2026-02-16T20:10:32.8376864Z"
}