{
  "Route": "/Error",
  "Url": "https://localhost:7161/Error",
  "StatusCode": 200,
  "FileSize": 52407,
  "IsSuspiciouslySmall": false,
  "RetryAttempted": false,
  "ConsoleErrors": [
    "Access to XMLHttpRequest at \u0027http://localhost:52002/81d8742caa484684bd5780caadd343bd/browserLinkSignalR/start?transport=webSockets\u0026clientProtocol=2.1\u0026requestUrl=https%3A%2F%2Flocalhost%3A7161%2FError\u0026browserName=\u0026userAgent=Mozilla%2F5.0%20(Windows%20NT%2010.0%3B%20Win64%3B%20x64)%20AppleWebKit%2F537.36%20(KHTML%2C%20like%20Gecko)%20HeadlessChrome%2F141.0.7390.37%20Safari%2F537.36\u0026browserIdKey=window.browserLink.initializationData.browserId\u0026browserId=0ae0-140f\u0026connectionToken=AQAAANCMnd8BFdERjHoAwE%2FCl%2BsBAAAABDp90XHsUkqffVEv%2Bu76MAAAAAACAAAAAAAQZgAAAAEAACAAAABV0UklBW6sY9mRDZJgnVxkrCxyyv6cudl49xlLu%2BZsyQAAAAAOgAAAAAIAACAAAACJtuu92kLezC0mSs0rs%2FPUpjKDCto9%2FXLPm0eUb5kKSDAAAABo8T7bXhDjbVoOnn2WD3o2CcoFAQgj0Oqdlh%2FF0%2BsBsU415LcoTekOvZ0px%2F7C2HRAAAAAOWdx3Sy3s58jWtpUxbXd7c651mCESEgTXPHd7PFD9JJjWpLJNKYfyNflzz836DZ3DymyucWtdXNCWfgBJyP9gw%3D%3D\u0026_=1767120674782\u0027 from origin \u0027https://localhost:7161\u0027 has been blocked by CORS policy: No \u0027Access-Control-Allow-Origin\u0027 header is present on the requested resource.",
    "Failed to load resource: net::ERR_FAILED",
    "Access to XMLHttpRequest at \u0027http://localhost:52002/81d8742caa484684bd5780caadd343bd/browserLinkSignalR/start?transport=webSockets\u0026clientProtocol=2.1\u0026requestUrl=https%3A%2F%2Flocalhost%3A7161%2FError\u0026browserName=\u0026userAgent=Mozilla%2F5.0%20(Windows%20NT%2010.0%3B%20Win64%3B%20x64)%20AppleWebKit%2F537.36%20(KHTML%2C%20like%20Gecko)%20HeadlessChrome%2F141.0.7390.37%20Safari%2F537.36\u0026browserIdKey=window.browserLink.initializationData.browserId\u0026browserId=77de-9c0c\u0026connectionToken=AQAAANCMnd8BFdERjHoAwE%2FCl%2BsBAAAABDp90XHsUkqffVEv%2Bu76MAAAAAACAAAAAAAQZgAAAAEAACAAAADYIbrwzFI6f4ZE6o2pWXxye0%2B2JLlcMm2tf%2F7sGi61CwAAAAAOgAAAAAIAACAAAACYZedBM7UYDaVCXEqjoURAYbvGNItS%2FovnK2IWFcnjAjAAAADrnrKFGvVviwybOqeLGCXYFtVaO49S7CAnXkN9dO%2FHhiOFXZyRnfRg4%2F4i8qkfhF5AAAAAayIUMZnF0DQlS6XYHKDihsi2ywgWhqqiaYntuCqy%2FsnSt8RFbB6Tyt9erkOLIhOy257Hw8H%2FOyWZI5FON5NspA%3D%3D\u0026_=1767120674784\u0027 from origin \u0027https://localhost:7161\u0027 has been blocked by CORS policy: No \u0027Access-Control-Allow-Origin\u0027 header is present on the requested resource.",
    "Failed to load resource: net::ERR_FAILED"
  ],
  "CapturedAt": "2025-12-30T18:51:13.6947787Z",
  "IsSuccess": true,
  "IsHttpError": false,
  "IsError": false,
  "ErrorMessage": null
}