{
  "PagePath": "/news/",
  "Url": "https://its.wsu.edu/news/",
  "FinalUrl": null,
  "Title": "News | Information Technology Services | Washington State University",
  "StatusCode": 200,
  "Success": true,
  "HtmlSizeBytes": 240381,
  "ScreenshotSizeBytes": 314285,
  "CredentialUsed": null,
  "ConsoleErrorCount": 0,
  "ConsoleWarningCount": 0,
  "Screenshots": [
    {
      "FileName": "01-page-loaded.jpg",
      "Label": "page-loaded",
      "StepNumber": 1,
      "FileSize": 314285
    }
  ],
  "ImageCount": 0,
  "ImagesMissingAlt": 0,
  "Images": [],
  "Accessibility": {
    "ToolsRun": [
      "axe",
      "htmlcheck"
    ],
    "ToolsSkipped": [
      "wave"
    ],
    "TotalViolations": 7,
    "Critical": 0,
    "Serious": 7,
    "Moderate": 0,
    "Minor": 0,
    "ByTool": {
      "axe": {
        "Total": 1,
        "Critical": 0,
        "Serious": 1,
        "Moderate": 0,
        "Minor": 0
      },
      "htmlcheck": {
        "Total": 6,
        "Critical": 0,
        "Serious": 6,
        "Moderate": 0,
        "Minor": 0
      }
    }
  },
  "ErrorMessage": null,
  "Headers": {
    "content-encoding": "gzip",
    "content-type": "text/html; charset=UTF-8",
    "date": "Thu, 19 Feb 2026 02:20:20 GMT",
    "etag": "\u0022c69f74a39ecbc68393408dfbe0f9daef\u0022",
    "last-modified": "Thu, 19 Feb 2026 02:20:20 GMT",
    "link": "\u003Chttps://its.wsu.edu/wp-json/\u003E; rel=\u0022https://api.w.org/\u0022",
    "server": "nginx",
    "vary": "Accept-Encoding",
    "x-tec-api-origin": "https://its.wsu.edu",
    "x-tec-api-root": "https://its.wsu.edu/wp-json/tribe/events/v1/",
    "x-tec-api-version": "v1"
  },
  "CapturedAt": "2026-02-19T02:20:19.8688042Z"
}